csv2sqlite/__init__.py
csv2sqlite/__main__.py
csv2sqlite/cli.py
csv2sqlite-0.3.0.dist-info/METADATA
csv2sqlite-0.3.0.dist-info/RECORD
csv2sqlite-0.3.0.dist-info/WHEEL
csv2sqlite-0.3.0.dist-info/entry_points.txt
csv2sqlite-0.3.0.dist-info/top_level.txt
